deepgeo_ext_yolo/Config.py
deepgeo_ext_yolo/Dataset.py
deepgeo_ext_yolo/Model.py
deepgeo_ext_yolo/__init__.py
deepgeo_ext_yolo-0.0.1.dist-info/LICENSE
deepgeo_ext_yolo-0.0.1.dist-info/METADATA
deepgeo_ext_yolo-0.0.1.dist-info/WHEEL
deepgeo_ext_yolo-0.0.1.dist-info/top_level.txt
deepgeo_ext_yolo-0.0.1.dist-info/RECORD
