Metadata-Version: 2.1
Name: deepgeo-ext-yolo
Version: 0.0.1
Summary: deepgeo_ext_yolo
Home-page: https://github.com/Sotaneum/deepgeo_ext_yolo
Author: Donggun LEE
Author-email: gnyotnu39@gmail.com
License: MIT
Platform: UNKNOWN
Classifier: License :: OSI Approved :: MIT License
Requires-Dist: deepgeo (>=0.2.0)
Requires-Dist: numpy
Requires-Dist: opencv-python
